nitrate/__init__.py
nitrate/base.py
nitrate/cache.py
nitrate/config.py
nitrate/containers.py
nitrate/immutable.py
nitrate/mutable.py
nitrate/teiid.py
nitrate/tests.py
nitrate/utils.py
nitrate/xmlrpc_driver.py
nitrate-1.9.0.data/scripts/nitrate
nitrate-1.9.0.dist-info/LICENSE
nitrate-1.9.0.dist-info/METADATA
nitrate-1.9.0.dist-info/WHEEL
nitrate-1.9.0.dist-info/top_level.txt
nitrate-1.9.0.dist-info/RECORD
