Metadata-Version: 2.1
Name: nitrate
Version: 1.9.0
Summary: Python API for the Nitrate test case management system
Home-page: https://psss.fedorapeople.org/python-nitrate/
Author: Petr Šplíchal
Author-email: psplicha@redhat.com
License: LGPLv2+
Classifier: Development Status :: 5 - Production/Stable
Classifier: Environment :: Console
Classifier: Intended Audience :: Developers
Classifier: Intended Audience :: System Administrators
Classifier: License :: OSI Approved :: GNU Lesser General Public License v2 or later (LGPLv2+)
Classifier: Operating System :: POSIX
Classifier: Programming Language :: Python
Classifier: Programming Language :: Python :: 2.7
Classifier: Programming Language :: Python :: 3.6
Classifier: Programming Language :: Python :: 3.7
Classifier: Topic :: Software Development
Classifier: Topic :: Software Development :: Libraries :: Python Modules
Classifier: Topic :: Software Development :: Quality Assurance
Classifier: Topic :: Software Development :: Testing
License-File: LICENSE
Requires-Dist: gssapi
Requires-Dist: psycopg2
Requires-Dist: six
